pydblite/common.py
pydblite/pydblite_conversions.py
pydblite/__init__.py
pydblite/sqlite.py
pydblite/pydblite.py
PyDbLite-3.0.1.dist-info/top_level.txt
PyDbLite-3.0.1.dist-info/METADATA
PyDbLite-3.0.1.dist-info/DESCRIPTION.rst
PyDbLite-3.0.1.dist-info/metadata.json
PyDbLite-3.0.1.dist-info/WHEEL
PyDbLite-3.0.1.dist-info/RECORD
