Metadata-Version: 2.0
Name: PyDbLite
Version: 3.0.1
Summary: PyDbLite, a fast, pure-Python in-memory database
